witty_flow_sms/__init__.py
witty_flow_sms-1.0.2.dist-info/LICENSE
witty_flow_sms-1.0.2.dist-info/METADATA
witty_flow_sms-1.0.2.dist-info/WHEEL
witty_flow_sms-1.0.2.dist-info/top_level.txt
witty_flow_sms-1.0.2.dist-info/RECORD
