Metadata-Version: 2.1
Name: witty-flow-sms
Version: 1.0.2
Summary: A Docker and AWS utility package
Home-page: https://github.com/charlesagyemang/first_pip_project
Author: Charles Opoku-Agyemang
Author-email: micnkru@gmail.com
License: UNKNOWN
Platform: UNKNOWN
Classifier: Programming Language :: Python :: 3
Classifier: License :: OSI Approved :: MIT License
Classifier: Operating System :: OS Independent
License-File: LICENSE
